LICENSE
MANIFEST.in
README
TODO
changes.rst
setup.cfg
setup.py
simples3/__init__.py
simples3/bucket.py
simples3/gae.py
simples3/streaming.py
simples3/utils.py
simples3.egg-info/PKG-INFO
simples3.egg-info/SOURCES.txt
simples3.egg-info/dependency_links.txt
simples3.egg-info/top_level.txt
tests/__init__.py
tests/test_bucket.py
tests/test_urls.py