Metadata-Version: 1.0
Name: simples3
Version: 1.0
Summary: Simple, quick Amazon AWS S3 interface
Home-page: http://sendapatch.se/projects/simples3/
Author: Ludvig Ericson
Author-email: ludvig@lericson.se
License: UNKNOWN
Platform: UNKNOWN
